{
  "note": "Live terminology-server endpoints, sourced from data/digital_tablet_omnibus.json (_digitalTablet.terminology_servers). Used ONLY in live mode; mock mode NEVER calls them. Live NCTS/Ontoserver grounding of SNOMED CT-AU content requires an NCTS licence/account (input-gated). These are public reference URLs, not secrets.",
  "primary": "https://r4.ontoserver.csiro.au/fhir",
  "servers": {
    "NCTS_Ontoserver": "https://r4.ontoserver.csiro.au/fhir",
    "SNOMED_browser": "https://browser.ihtsdotools.org",
    "LOINC_search": "https://loinc.org/search",
    "TGA_ARTG": "https://www.tga.gov.au/resources/artg"
  },
  "code_system_versions": {
    "SNOMED_CT": "SNOMED CT Australian Edition 20240301",
    "ICD_10_AM": "ICD-10-AM 12th Edition",
    "ICD_11": "ICD-11",
    "LOINC": "2.77",
    "PBS": "current (no live PBS API connected)",
    "AMT": "Australian Medicines Terminology (AMT subset not yet validated)"
  }
}
