{
  "case_id": "SPEC-GP-03-00014",
  "demographics": {
    "age": 45,
    "sex_at_birth": "male",
    "living_situation": "lives in a private residence",
    "language_and_literacy": {
      "primary_language": "English",
      "english_proficiency": "fluent",
      "health_literacy_level": "moderate"
    }
  },
  "opening_complaint": {
    "verbatim_patient_text": "I went swimming, water got in my ear, and now I'm completely deaf on that side and the pressure is agonizing.",
    "stated_reason_for_presenting_today": "My right ear suddenly blocked up and became agonizingly painful a few hours ago right after I went swimming, and now I can't hear anything on that side.",
    "encounter_type_patient_expectation": "seeking_diagnosis"
  },
  "history_as_reported": {
    "symptom_narrative": {
      "onset": "a few hours ago, right after I went swimming and water got into the ear",
      "duration": "about 4 hours and it has been getting worse",
      "character": "a completely full, blocked feeling with intense deep pressure inside the ear",
      "severity_patient_description": "agonizing — the worst ear pressure I have ever felt",
      "location_as_patient_describes": "deep inside my right ear",
      "timing_pattern": "constant since it started",
      "what_makes_it_better": "nothing has helped so far",
      "what_makes_it_worse": "it came on after water got in; I tried drying it with a hairdryer and that didn't help",
      "associated_symptoms_volunteered": "a new loud low-pitched roaring noise in that ear, and I feel a bit off-balance and disoriented from suddenly not being able to hear",
      "previous_episodes": "nothing like this before, but I've always used cotton buds to clean my ears",
      "functional_impact": "I'm very distressed and disoriented by suddenly being deaf on one side"
    },
    "past_medical_history": [
      {
        "condition_as_patient_states": "My eardrums have always been intact and I've never had any ear surgery."
      }
    ],
    "current_medications_as_reported": [],
    "social_history_volunteered": {
      "relevant_life_context": "Regularly cleans ears with cotton buds; went swimming today; attempted to dry the ear with a hairdryer afterwards."
    }
  },
  "objective_data_offered": [
    {
      "type": "hearing_self_check",
      "value": "I can't hear my own fingers rubbing right next to my right ear at all, but the left is fine.",
      "source": "patient_reported",
      "verified": false,
      "reliability_caveat": "gross self-administered hearing check reported by the patient, not formal audiometry"
    }
  ]
}
