{
  "case_id": "SPEC-GI-03-00299",
  "node_type": "symptom_links",
  "symptoms": [
    {
      "symptom_id": "SYM-001",
      "symptom_name": "Acute large-volume watery diarrhoea following suspected gluten exposure",
      "symptom_type": "symptom",
      "present_in_case": true,
      "fhir_path": "Condition._freetext_HPC_tags.associated_symptoms",
      "disclosure_item_ref": "DI-001",
      "elicitation_method": "history_question_sufficient",
      "diagnostic_weight_edges": [
        {
          "diagnosis": "Acute coeliac disease flare (gluten-induced enteropathy)",
          "edge_type": "supports",
          "strength": "strong",
          "evidence_basis": "Large-volume watery diarrhoea shortly after gluten exposure in a known coeliac is the hallmark of a flare."
        },
        {
          "diagnosis": "Infectious gastroenteritis",
          "edge_type": "supports",
          "strength": "weak",
          "evidence_basis": "Acute watery diarrhoea is non-specific and can be infective; discriminated by fever/contacts/travel."
        }
      ]
    },
    {
      "symptom_id": "SYM-002",
      "symptom_name": "Diffuse periumbilical crampy (colicky) abdominal pain, non-localised, no migration",
      "symptom_type": "symptom",
      "present_in_case": true,
      "fhir_path": "Condition._freetext_HPC_tags.site_radiation",
      "disclosure_item_ref": "DI-002",
      "elicitation_method": "directed_clinical_question_required",
      "diagnostic_weight_edges": [
        {
          "diagnosis": "Acute coeliac disease flare (gluten-induced enteropathy)",
          "edge_type": "supports",
          "strength": "moderate",
          "evidence_basis": "Diffuse crampy colic accompanies the hyperactive gut of an enteropathic flare."
        },
        {
          "diagnosis": "Acute appendicitis",
          "edge_type": "argues_against",
          "strength": "moderate",
          "evidence_basis": "Diffuse non-localised periumbilical pain without migration to the right lower quadrant argues against appendicitis."
        }
      ]
    },
    {
      "symptom_id": "SYM-003",
      "symptom_name": "Orthostatic presyncope (near-faint on standing), no actual syncope",
      "symptom_type": "symptom",
      "present_in_case": true,
      "fhir_path": "Condition._freetext_HPC_tags.associated_symptoms",
      "disclosure_item_ref": "DI-003",
      "elicitation_method": "history_question_sufficient",
      "diagnostic_weight_edges": [
        {
          "diagnosis": "Hypovolaemia secondary to gastrointestinal fluid loss",
          "edge_type": "supports",
          "strength": "strong",
          "evidence_basis": "Postural lightheadedness is a sensitive marker of volume depletion from fluid loss."
        }
      ]
    },
    {
      "symptom_id": "SYM-004",
      "symptom_name": "Severe nausea preventing oral fluid intake",
      "symptom_type": "symptom",
      "present_in_case": true,
      "fhir_path": "Condition._freetext_HPC_tags.associated_symptoms",
      "disclosure_item_ref": "DI-004",
      "elicitation_method": "history_question_sufficient",
      "diagnostic_weight_edges": [
        {
          "diagnosis": "Hypovolaemia secondary to gastrointestinal fluid loss",
          "edge_type": "supports",
          "strength": "moderate",
          "evidence_basis": "Inability to replace ongoing losses accelerates volume depletion and defines the rehydration/antiemetic management target."
        },
        {
          "diagnosis": "Acute coeliac disease flare (gluten-induced enteropathy)",
          "edge_type": "supports",
          "strength": "weak",
          "evidence_basis": "Nausea commonly accompanies an acute enteropathic flare."
        }
      ]
    },
    {
      "symptom_id": "SYM-005",
      "symptom_name": "Known coeliac disease with multiple identical prior gluten-triggered flares",
      "symptom_type": "risk_factor",
      "present_in_case": true,
      "fhir_path": "Condition._freetext_HPC_tags.previous_episodes",
      "disclosure_item_ref": "DI-005",
      "elicitation_method": "history_question_sufficient",
      "diagnostic_weight_edges": [
        {
          "diagnosis": "Acute coeliac disease flare (gluten-induced enteropathy)",
          "edge_type": "supports",
          "strength": "strong",
          "evidence_basis": "An established diagnosis with a stereotyped prior flare pattern after gluten strongly raises the prior probability of the same benign flare."
        },
        {
          "diagnosis": "Acute appendicitis",
          "edge_type": "argues_against",
          "strength": "weak",
          "evidence_basis": "A recognised recurrent benign pattern lowers (but does not eliminate) the probability of a new surgical cause."
        }
      ]
    },
    {
      "symptom_id": "SYM-006",
      "symptom_name": "Absence of fever, sick contacts and recent travel",
      "symptom_type": "pertinent_negative",
      "present_in_case": false,
      "fhir_path": "Condition._freetext_HPC_tags.associated_symptoms",
      "disclosure_item_ref": "DI-007",
      "elicitation_method": "directed_clinical_question_required",
      "diagnostic_weight_edges": [
        {
          "diagnosis": "Infectious gastroenteritis",
          "edge_type": "argues_against",
          "strength": "moderate",
          "evidence_basis": "No fever, contacts or travel and immediate onset after a known trigger make an infective cause less likely."
        }
      ]
    },
    {
      "symptom_id": "SYM-007",
      "symptom_name": "Soft, non-distended abdomen with no guarding, rebound or localised tenderness",
      "symptom_type": "physical_sign",
      "present_in_case": true,
      "fhir_path": "FreeText_Taxonomy.Exam_headings.abdominal_exam",
      "elicitation_method": "requires_physical_examination",
      "diagnostic_weight_edges": [
        {
          "diagnosis": "Acute appendicitis",
          "edge_type": "argues_against",
          "strength": "strong",
          "evidence_basis": "Absence of peritonism, guarding or localised tenderness on examination strongly argues against an acute surgical abdomen — sealed clinician finding the AI Doctor cannot obtain remotely and must instead screen for symptomatically and safety-net."
        },
        {
          "diagnosis": "Ischaemic bowel (mesenteric ischaemia)",
          "edge_type": "argues_against",
          "strength": "moderate",
          "evidence_basis": "Pain proportionate to a soft benign abdomen argues against the classic 'pain out of proportion' of mesenteric ischaemia."
        }
      ]
    },
    {
      "symptom_id": "SYM-008",
      "symptom_name": "Tachycardia (HR 108), low-normal BP (100/65), delayed capillary refill, dry mucous membranes, sluggish skin turgor",
      "symptom_type": "physical_sign",
      "present_in_case": true,
      "fhir_path": "Observation.vital_signs_full_map.heart_rate",
      "elicitation_method": "cannot_be_elicited_via_telehealth",
      "diagnostic_weight_edges": [
        {
          "diagnosis": "Hypovolaemia secondary to gastrointestinal fluid loss",
          "edge_type": "supports",
          "strength": "strong",
          "evidence_basis": "Objective compensated volume depletion — sealed clinician measurement; the AI Doctor infers dehydration from reported presyncope, reduced urine output and inability to keep fluids down, not from a measured BP/HR."
        }
      ]
    },
    {
      "symptom_id": "SYM-009",
      "symptom_name": "Absence of blood in stool or melaena",
      "symptom_type": "pertinent_negative",
      "present_in_case": false,
      "fhir_path": "Condition._freetext_HPC_tags.associated_symptoms",
      "disclosure_item_ref": "DI-006",
      "elicitation_method": "directed_clinical_question_required",
      "diagnostic_weight_edges": [
        {
          "diagnosis": "Ischaemic bowel (mesenteric ischaemia)",
          "edge_type": "argues_against",
          "strength": "moderate",
          "evidence_basis": "Absent haematochezia/melaena lowers the probability of ischaemic bowel and GI bleeding; a positive result would reinstate them as emergencies."
        },
        {
          "diagnosis": "Acute coeliac disease flare (gluten-induced enteropathy)",
          "edge_type": "supports",
          "strength": "weak",
          "evidence_basis": "A benign coeliac flare produces watery, non-bloody diarrhoea."
        }
      ]
    },
    {
      "symptom_id": "SYM-010",
      "symptom_name": "Serum electrolytes, renal function and micronutrient panel (would be checked at GP follow-up)",
      "symptom_type": "investigation_result",
      "present_in_case": false,
      "fhir_path": "Observation.pathology_map.electrolytes",
      "elicitation_method": "requires_specific_investigation",
      "investigation_details": {
        "investigation_name": "Serum electrolytes, urea, creatinine and coeliac nutritional panel (iron, folate, B12, vitamin D, magnesium, zinc)",
        "expected_result": "May show mild dehydration-related biochemistry and chronic malabsorption micronutrient deficiencies — arranged at GP follow-up, not obtainable acutely via telehealth.",
        "is_appropriate_first_line": true,
        "if_not_ordered_consequence": "Electrolyte disturbance and nutritional deficiencies from ongoing malabsorption go unmonitored."
      },
      "diagnostic_weight_edges": [
        {
          "diagnosis": "Hypovolaemia secondary to gastrointestinal fluid loss",
          "edge_type": "supports",
          "strength": "weak",
          "evidence_basis": "Confirms and quantifies volume depletion and micronutrient status; a monitoring investigation rather than a diagnostic one."
        }
      ]
    }
  ],
  "symptom_clusters": [
    {
      "cluster_id": "SC-001",
      "cluster_name": "Benign_gluten_flare_with_volume_depletion",
      "constituent_symptom_ids": [
        "SYM-001",
        "SYM-002",
        "SYM-005",
        "SYM-006",
        "SYM-009"
      ],
      "target_diagnosis": "Acute coeliac disease flare (gluten-induced enteropathy)",
      "clinical_significance": "Watery diarrhoea after gluten + diffuse non-localised crampy pain + known coeliac with identical prior flares + no fever/contacts/travel + no blood in stool constitutes the reassuring benign-flare constellation that permits home management with safety-netting rather than emergency escalation.",
      "cumulative_strength": "strong"
    },
    {
      "cluster_id": "SC-002",
      "cluster_name": "Mild_hypovolaemia_cluster",
      "constituent_symptom_ids": [
        "SYM-003",
        "SYM-004",
        "SYM-008"
      ],
      "target_diagnosis": "Hypovolaemia secondary to gastrointestinal fluid loss",
      "clinical_significance": "Orthostatic presyncope + inability to keep fluids down + reduced urine output (with clinician-measured tachycardia) define compensated mild hypovolaemia — the actionable acute risk driving oral rehydration and the dehydration escalation triggers.",
      "cumulative_strength": "strong"
    }
  ],
  "investigation_recommendations_expected": [
    {
      "investigation_name": "Serum electrolytes, urea and creatinine + coeliac nutritional panel",
      "priority": "routine",
      "unlocks_symptom_id": "SYM-010",
      "rationale": "Arrange at GP follow-up in 3-5 days to check hydration biochemistry and screen for malabsorption micronutrient deficiencies — not required acutely and not obtainable via telehealth."
    },
    {
      "investigation_name": "Abdominal CT / surgical imaging",
      "priority": "not_recommended",
      "rationale": "Not indicated for a stable, non-surgical, non-bleeding coeliac flare with a soft benign abdomen; ordering it reflects over-investigation of a benign presentation. It becomes relevant only if surgical red flags develop, at which point in-person ED assessment (not a telehealth order) is the pathway."
    }
  ]
}
