{
  "case_id": "SPEC-OPHTH-01-00048",
  "demographics": {
    "age": 32,
    "sex_at_birth": "male",
    "living_situation": "lives alone",
    "language_and_literacy": {
      "primary_language": "English",
      "english_proficiency": "fluent",
      "health_literacy_level": "moderate"
    },
    "contact_nok": {
      "relationship": "none stated",
      "available": false
    }
  },
  "opening_complaint": {
    "verbatim_patient_text": "My eyes are bright red, they feel like they're full of sand, and I can barely see through the constant watering.",
    "stated_reason_for_presenting_today": "Both eyes went red and gritty with watering after a cold and I want to be sure it's not serious.",
    "encounter_type_patient_expectation": "seeking_reassurance"
  },
  "history_as_reported": {
    "symptom_narrative": {
      "onset": "24h ago in one eye, spread to the other",
      "duration": "24h",
      "character": "red, gritty/sandy, watery discharge, morning crusting (not thick pus), mild lid swelling, blur that clears when wiped",
      "severity_patient_description": "bright red, sandy, watering",
      "location_as_patient_describes": "both eyes",
      "timing_pattern": "one eye then the other",
      "what_makes_it_better": "wiping the discharge",
      "what_makes_it_worse": "nothing specific",
      "associated_symptoms_volunteered": "sore throat/runny nose 3 days ago; NO severe deep eye pain, no light sensitivity, no halos, vision normal once wiped",
      "previous_episodes": "none",
      "functional_impact": "blurred by tearing; worried about work contacts"
    },
    "past_medical_history": [],
    "current_medications_as_reported": [
      {
        "name_as_patient_states": "saline drops",
        "dose_as_patient_reports": "minimal relief",
        "adherence_as_reported": "irregular",
        "otc_or_herbal": true
      }
    ],
    "allergies_as_reported": [
      {
        "substance": "no known drug allergy",
        "reaction_described": "none known"
      }
    ],
    "family_history_as_reported": [],
    "social_history_volunteered": {
      "relevant_life_context": "lives alone; recent URI; contagion risk to colleagues"
    }
  },
  "objective_data_offered": [
    {
      "type": "eyes",
      "value": "both eyes red with watery discharge and morning crusting, mild lid swelling, visible on video",
      "source": "video_observable",
      "verified": false
    },
    {
      "type": "vision",
      "value": "vision normal once the discharge is wiped; no deep pain, no light sensitivity, no halos",
      "source": "patient_reported",
      "verified": false,
      "reliability_caveat": "self-assessed vision"
    }
  ],
  "digital_tablet_field_map": {
    "chief_complaint_path": "Condition._freetext_HPC_tags",
    "demographics_path": "Patient",
    "medications_path": "MedicationRequest"
  }
}
