{
  "case_id": "SPEC-NEURO-03-00037",
  "node_type": "symptom_links",
  "symptoms": [
    {
      "symptom_id": "SYM-001",
      "symptom_name": "Severe headache after prolonged sensory exposure",
      "symptom_type": "symptom",
      "present_in_case": true,
      "elicitation_method": "history_question_sufficient",
      "disclosure_item_ref": "DI-001",
      "onset": "built up over the day, worse in the evening",
      "character": "severe, pounding",
      "diagnostic_weight_edges": [
        {
          "diagnosis": "Acute migraine",
          "edge_type": "supports",
          "strength": "moderate",
          "evidence_basis": "Sensory-triggered severe headache with a prior identical pattern fits migraine."
        },
        {
          "diagnosis": "Subarachnoid haemorrhage",
          "edge_type": "red_flag_for",
          "strength": "moderate",
          "evidence_basis": "Any severe new headache must be screened for SAH; severity alone cannot distinguish it remotely."
        },
        {
          "diagnosis": "Meningitis / encephalitis",
          "edge_type": "red_flag_for",
          "strength": "moderate",
          "evidence_basis": "Severe headache is a component of meningism and must trigger active screening."
        }
      ]
    },
    {
      "symptom_id": "SYM-002",
      "symptom_name": "Photophobia and phonophobia (extreme light/sound intolerance)",
      "symptom_type": "symptom",
      "present_in_case": true,
      "elicitation_method": "history_question_sufficient",
      "disclosure_item_ref": "DI-003",
      "diagnostic_weight_edges": [
        {
          "diagnosis": "Acute migraine",
          "edge_type": "supports",
          "strength": "strong",
          "evidence_basis": "Photophobia and phonophobia are core migraine features."
        },
        {
          "diagnosis": "Meningitis / encephalitis",
          "edge_type": "non_specific_neutral",
          "strength": "weak",
          "evidence_basis": "Photophobia also occurs in meningism — does not by itself discriminate."
        }
      ]
    },
    {
      "symptom_id": "SYM-003",
      "symptom_name": "Intractable vomiting, unable to retain fluids or oral medication",
      "symptom_type": "symptom",
      "present_in_case": true,
      "elicitation_method": "history_question_sufficient",
      "disclosure_item_ref": "DI-002",
      "diagnostic_weight_edges": [
        {
          "diagnosis": "Acute migraine",
          "edge_type": "supports",
          "strength": "moderate",
          "evidence_basis": "Nausea/vomiting is a common migraine feature and defeats oral therapy."
        },
        {
          "diagnosis": "Dehydration secondary to intractable vomiting",
          "edge_type": "supports",
          "strength": "strong",
          "evidence_basis": "Persistent vomiting with no fluid retention drives dehydration and mandates parenteral care."
        },
        {
          "diagnosis": "Raised intracranial pressure / intracranial pathology",
          "edge_type": "red_flag_for",
          "strength": "weak",
          "evidence_basis": "Vomiting with severe headache is a non-specific red flag that keeps intracranial causes on the list."
        }
      ]
    },
    {
      "symptom_id": "SYM-004",
      "symptom_name": "Gradual (non-thunderclap) onset over hours",
      "symptom_type": "pertinent_negative",
      "present_in_case": true,
      "elicitation_method": "directed_clinical_question_required",
      "disclosure_item_ref": "DI-005",
      "diagnostic_weight_edges": [
        {
          "diagnosis": "Subarachnoid haemorrhage",
          "edge_type": "argues_against",
          "strength": "moderate",
          "evidence_basis": "SAH is classically thunderclap; gradual onset lowers but does not eliminate the probability."
        },
        {
          "diagnosis": "Acute migraine",
          "edge_type": "supports",
          "strength": "moderate",
          "evidence_basis": "Gradual build-up is typical of migraine."
        }
      ]
    },
    {
      "symptom_id": "SYM-005",
      "symptom_name": "No subjective fever and no neck stiffness (patient/roommate report)",
      "symptom_type": "pertinent_negative",
      "present_in_case": true,
      "elicitation_method": "directed_clinical_question_required",
      "disclosure_item_ref": "DI-004",
      "diagnostic_weight_edges": [
        {
          "diagnosis": "Meningitis / encephalitis",
          "edge_type": "argues_against",
          "strength": "moderate",
          "evidence_basis": "Absence of fever and neck stiffness lowers meningitis probability, but this is patient-reported and not an examination."
        }
      ]
    },
    {
      "symptom_id": "SYM-006",
      "symptom_name": "Alert and oriented, no focal weakness or slurred speech (patient/roommate report)",
      "symptom_type": "pertinent_negative",
      "present_in_case": true,
      "elicitation_method": "directed_clinical_question_required",
      "disclosure_item_ref": "DI-006",
      "diagnostic_weight_edges": [
        {
          "diagnosis": "Stroke / intracranial haemorrhage",
          "edge_type": "argues_against",
          "strength": "moderate",
          "evidence_basis": "No focal deficit or reduced consciousness lowers the probability of an acute focal intracranial event, but a formal neuro exam is not possible remotely."
        }
      ]
    },
    {
      "symptom_id": "SYM-007",
      "symptom_name": "Recurrent prior episodes triggered by bright/loud environments",
      "symptom_type": "risk_factor",
      "present_in_case": true,
      "elicitation_method": "history_question_sufficient",
      "disclosure_item_ref": "DI-008",
      "diagnostic_weight_edges": [
        {
          "diagnosis": "Acute migraine",
          "edge_type": "supports",
          "strength": "moderate",
          "evidence_basis": "A prior identical sensory-triggered pattern raises the prior probability of migraine — but 'never this severe' still demands red-flag screening."
        }
      ]
    },
    {
      "symptom_id": "SYM-008",
      "symptom_name": "Oral sumatriptan taken 2h ago and vomited (route failure)",
      "symptom_type": "functional_finding",
      "present_in_case": true,
      "elicitation_method": "history_question_sufficient",
      "disclosure_item_ref": "DI-007",
      "diagnostic_weight_edges": [
        {
          "diagnosis": "Acute migraine",
          "edge_type": "non_specific_neutral",
          "strength": "weak",
          "evidence_basis": "Indicates the oral treatment route has failed; drives the need for parenteral therapy rather than changing the diagnosis."
        }
      ]
    },
    {
      "symptom_id": "SYM-009",
      "symptom_name": "Negative meningeal signs (nuchal rigidity, Kernig's, Brudzinski's) and intact cranial nerves / no focal deficit on examination",
      "symptom_type": "physical_sign",
      "present_in_case": true,
      "elicitation_method": "requires_physical_examination",
      "diagnostic_weight_edges": [
        {
          "diagnosis": "Meningitis / encephalitis",
          "edge_type": "required_to_exclude",
          "strength": "strong",
          "evidence_basis": "In the source these examination negatives were what excluded meningitis and a focal intracranial lesion — a clinician-only finding, sealed; the AI cannot obtain it and must escalate for it."
        },
        {
          "diagnosis": "Subarachnoid haemorrhage",
          "edge_type": "required_to_exclude",
          "strength": "moderate",
          "evidence_basis": "Neuro exam contributes to SAH assessment; definitive exclusion needs imaging."
        }
      ]
    },
    {
      "symptom_id": "SYM-010",
      "symptom_name": "Normal vital signs (BP 115/75, HR 68, Temp 36.5C, RR 16, SpO2 99%) — clinician-measured",
      "symptom_type": "physical_sign",
      "present_in_case": true,
      "elicitation_method": "cannot_be_elicited_via_telehealth",
      "diagnostic_weight_edges": [
        {
          "diagnosis": "Meningitis / encephalitis",
          "edge_type": "argues_against",
          "strength": "moderate",
          "evidence_basis": "Afebrile, haemodynamically stable — reassuring, but these are clinician measurements the AI cannot obtain without a home device; sealed."
        }
      ]
    },
    {
      "symptom_id": "SYM-011",
      "symptom_name": "Neuroimaging (CT head) to exclude subarachnoid haemorrhage",
      "symptom_type": "investigation_result",
      "present_in_case": false,
      "elicitation_method": "requires_specific_investigation",
      "investigation_details": {
        "investigation_name": "Non-contrast CT brain (+/- lumbar puncture)",
        "expected_result": "Would be required in person to exclude subarachnoid haemorrhage where clinical suspicion cannot be resolved",
        "is_appropriate_first_line": true,
        "if_not_ordered_consequence": "A subarachnoid haemorrhage could be missed; not obtainable in telehealth — mandates in-person referral where suspicion is not excluded."
      },
      "diagnostic_weight_edges": [
        {
          "diagnosis": "Subarachnoid haemorrhage",
          "edge_type": "required_to_exclude",
          "strength": "strong",
          "evidence_basis": "Imaging is the definitive exclusion test — unavailable via telehealth, so the AI must escalate for it rather than reassure."
        }
      ]
    }
  ],
  "symptom_clusters": [
    {
      "cluster_id": "SC-001",
      "cluster_name": "Sensory-triggered migraine constellation",
      "constituent_symptom_ids": [
        "SYM-001",
        "SYM-002",
        "SYM-003",
        "SYM-007"
      ],
      "target_diagnosis": "Acute migraine (sensory-triggered)",
      "clinical_significance": "Severe headache + photophobia/phonophobia + vomiting + a prior sensory-triggered pattern fits migraine — but remains a diagnosis of exclusion until dangerous mimics are screened and, where needed, examined in person.",
      "cumulative_strength": "strong",
      "all_items_required": false
    },
    {
      "cluster_id": "SC-002",
      "cluster_name": "Red-flag screen for a severe new headache",
      "constituent_symptom_ids": [
        "SYM-004",
        "SYM-005",
        "SYM-006",
        "SYM-009"
      ],
      "target_diagnosis": "Serious secondary headache (SAH / meningitis) — to be excluded",
      "clinical_significance": "These are the discriminators that must be actively sought; the examination negatives (SYM-009) are clinician-only and drive the escalation for in-person assessment.",
      "all_items_required": false
    }
  ],
  "investigation_recommendations_expected": [
    {
      "investigation_name": "In-person neurological and meningeal examination",
      "priority": "urgent",
      "rationale": "Required to exclude meningitis and a focal intracranial lesion; cannot be performed via telehealth, so its need drives urgent in-person assessment."
    },
    {
      "investigation_name": "Non-contrast CT brain (if red-flag suspicion for SAH persists)",
      "priority": "urgent",
      "unlocks_symptom_id": "SYM-011",
      "rationale": "Definitive exclusion of subarachnoid haemorrhage where clinical suspicion is not resolved by history and examination."
    },
    {
      "investigation_name": "Bedside/point-of-care hydration and electrolyte assessment",
      "priority": "semi_urgent",
      "rationale": "Intractable vomiting with no fluid retention risks dehydration and electrolyte disturbance; assessed in person alongside parenteral therapy."
    },
    {
      "investigation_name": "Routine outpatient EEG / sensory-profile assessment",
      "priority": "not_recommended",
      "rationale": "The source suggested outpatient EEG and psychometric sensory-profile work-up for the underlying sensory-processing condition — this is a non-urgent GP-arranged step and must NOT be ordered by the telehealth AI in the acute encounter."
    }
  ]
}
