{
  "case_id": "SPEC-GERI-04-00237",
  "node_type": "symptom_links",
  "symptoms": [
    {
      "symptom_id": "SYM-001",
      "symptom_name": "Recurrent syncope/near-syncope within 60-90 minutes of a meal",
      "symptom_type": "symptom",
      "present_in_case": true,
      "elicitation_method": "history_question_sufficient",
      "disclosure_item_ref": "DI-001",
      "onset": "5 days ago",
      "duration": "reproducibly post-prandial (after lunch), 3 episodes",
      "diagnostic_weight_edges": [
        {
          "diagnosis": "Postprandial hypotension with syncope",
          "edge_type": "pathognomonic_for",
          "strength": "strong",
          "evidence_basis": "A strict, reproducible meal-temporal relationship is highly characteristic of postprandial hypotension."
        },
        {
          "diagnosis": "Cardiac arrhythmia",
          "edge_type": "required_to_exclude",
          "strength": "strong",
          "evidence_basis": "Recurrent unexplained syncope always requires exclusion of an arrhythmic cause before a benign attribution."
        }
      ]
    },
    {
      "symptom_id": "SYM-002",
      "symptom_name": "Lightheadedness, visual disturbance and legs giving way on standing after meals",
      "symptom_type": "symptom",
      "present_in_case": true,
      "elicitation_method": "history_question_sufficient",
      "disclosure_item_ref": "DI-002",
      "aggravating_factors": [
        "standing up after a large meal"
      ],
      "relieving_factors": [
        "lying down",
        "remaining seated"
      ],
      "diagnostic_weight_edges": [
        {
          "diagnosis": "Postprandial hypotension with syncope",
          "edge_type": "supports",
          "strength": "strong",
          "evidence_basis": "Global cerebral hypoperfusion on postural change compounding post-meal splanchnic pooling."
        },
        {
          "diagnosis": "Orthostatic hypotension",
          "edge_type": "supports",
          "strength": "moderate",
          "evidence_basis": "Symptoms on standing overlap with postural hypotension; the two frequently coexist in autonomic failure."
        }
      ]
    },
    {
      "symptom_id": "SYM-003",
      "symptom_name": "No chest pain, palpitations or breathlessness before collapse",
      "symptom_type": "pertinent_negative",
      "present_in_case": true,
      "elicitation_method": "directed_clinical_question_required",
      "disclosure_item_ref": "DI-003",
      "diagnostic_weight_edges": [
        {
          "diagnosis": "Cardiac arrhythmia",
          "edge_type": "argues_against",
          "strength": "weak",
          "evidence_basis": "Reduces but does not exclude an arrhythmic cause — many arrhythmias are asymptomatic before syncope."
        }
      ]
    },
    {
      "symptom_id": "SYM-004",
      "symptom_name": "Known Parkinson's disease (autonomic dysfunction substrate)",
      "symptom_type": "risk_factor",
      "present_in_case": true,
      "elicitation_method": "history_question_sufficient",
      "disclosure_item_ref": "DI-004",
      "diagnostic_weight_edges": [
        {
          "diagnosis": "Postprandial hypotension with syncope",
          "edge_type": "supports",
          "strength": "strong",
          "evidence_basis": "Parkinson's-related autonomic failure is a leading predisposing cause of postprandial and postural hypotension."
        }
      ]
    },
    {
      "symptom_id": "SYM-005",
      "symptom_name": "Morning rapid-acting antihypertensive (drug aggravator)",
      "symptom_type": "risk_factor",
      "present_in_case": true,
      "elicitation_method": "history_question_sufficient",
      "disclosure_item_ref": "DI-004",
      "diagnostic_weight_edges": [
        {
          "diagnosis": "Postprandial hypotension with syncope",
          "edge_type": "supports",
          "strength": "moderate",
          "evidence_basis": "A rapid-acting antihypertensive amplifies the post-meal blood-pressure fall; a modifiable contributor."
        }
      ]
    },
    {
      "symptom_id": "SYM-006",
      "symptom_name": "Documented postprandial systolic BP drop of at least 20 mmHg within 120 minutes",
      "symptom_type": "physical_sign",
      "present_in_case": true,
      "elicitation_method": "cannot_be_elicited_via_telehealth",
      "investigation_details": {
        "investigation_name": "Clinician-supervised pre- and post-meal blood pressure measurement",
        "expected_result": "Systolic fall of at least 20 mmHg within 120 minutes of eating (e.g. ~145/85 pre-meal to ~100/60 post-meal)",
        "is_appropriate_first_line": true,
        "if_not_ordered_consequence": "The confirmatory diagnostic finding is missed; benign attribution cannot be safely made."
      },
      "diagnostic_weight_edges": [
        {
          "diagnosis": "Postprandial hypotension with syncope",
          "edge_type": "pathognomonic_for",
          "strength": "definitive",
          "evidence_basis": "Meets the accepted diagnostic threshold for postprandial hypotension — a clinician measurement sealed from the AI Doctor."
        }
      ]
    },
    {
      "symptom_id": "SYM-007",
      "symptom_name": "Absent compensatory tachycardia despite hypotension",
      "symptom_type": "physical_sign",
      "present_in_case": true,
      "elicitation_method": "requires_physical_examination",
      "diagnostic_weight_edges": [
        {
          "diagnosis": "Autonomic dysfunction / autonomic failure",
          "edge_type": "supports",
          "strength": "strong",
          "evidence_basis": "Failure of the heart rate to rise as BP falls is a hallmark of autonomic failure — requires clinician measurement, not obtainable via chat."
        }
      ]
    },
    {
      "symptom_id": "SYM-008",
      "symptom_name": "Normal cardiac rhythm and no murmurs on auscultation; no new focal neurological deficit",
      "symptom_type": "physical_sign",
      "present_in_case": true,
      "elicitation_method": "requires_physical_examination",
      "diagnostic_weight_edges": [
        {
          "diagnosis": "Cardiac arrhythmia",
          "edge_type": "argues_against",
          "strength": "moderate",
          "evidence_basis": "Reassuring cardiovascular and neurological examination — but a snapshot exam cannot exclude a paroxysmal arrhythmia; ECG/monitoring still needed."
        },
        {
          "diagnosis": "Transient ischaemic attack",
          "edge_type": "argues_against",
          "strength": "moderate",
          "evidence_basis": "Absence of focal deficit reduces the likelihood of a focal ischaemic event."
        }
      ]
    },
    {
      "symptom_id": "SYM-009",
      "symptom_name": "12-lead ECG / ambulatory rhythm monitoring",
      "symptom_type": "investigation_result",
      "present_in_case": false,
      "elicitation_method": "requires_specific_investigation",
      "investigation_details": {
        "investigation_name": "12-lead ECG and, if indicated, ambulatory monitoring",
        "expected_result": "To exclude an arrhythmic cause of syncope",
        "is_appropriate_first_line": true,
        "if_not_ordered_consequence": "A dangerous arrhythmia (e.g. sick sinus syndrome, heart block) could be missed."
      },
      "diagnostic_weight_edges": [
        {
          "diagnosis": "Cardiac arrhythmia",
          "edge_type": "required_to_exclude",
          "strength": "strong",
          "evidence_basis": "Standard first-line investigation in recurrent unexplained syncope — never available in real time via telehealth."
        }
      ]
    }
  ],
  "symptom_clusters": [
    {
      "cluster_id": "SC-001",
      "cluster_name": "Postprandial autonomic syncope tetrad",
      "constituent_symptom_ids": [
        "SYM-001",
        "SYM-002",
        "SYM-006",
        "SYM-007"
      ],
      "target_diagnosis": "Postprandial hypotension with syncope",
      "clinical_significance": "Reproducible post-meal collapse + symptoms on standing + a measured postprandial BP drop + absent compensatory tachycardia together confirm the diagnosis — but two of the four require clinician measurement.",
      "cumulative_strength": "pathognomonic",
      "all_items_required": false
    }
  ],
  "investigation_recommendations_expected": [
    {
      "investigation_name": "Urgent in-person clinical assessment with pre/post-meal and lying-standing blood pressure",
      "priority": "urgent",
      "unlocks_symptom_id": "SYM-006",
      "rationale": "Confirms postprandial/postural hypotension and cannot be done remotely."
    },
    {
      "investigation_name": "12-lead ECG (and monitoring if indicated)",
      "priority": "urgent",
      "unlocks_symptom_id": "SYM-009",
      "rationale": "Excludes an arrhythmic cause of recurrent syncope."
    },
    {
      "investigation_name": "Full blood examination and U&E/creatinine",
      "priority": "urgent",
      "rationale": "Excludes anaemia (occult GI bleed) and dehydration/renal contributors to syncope."
    }
  ]
}
