{
  "case_id": "SPEC-RHEUM-02-00205",
  "demographics": {
    "age": 38,
    "sex_at_birth": "female",
    "living_situation": "lives alone",
    "language_and_literacy": {
      "primary_language": "English",
      "english_proficiency": "fluent",
      "health_literacy_level": "moderate"
    }
  },
  "opening_complaint": {
    "verbatim_patient_text": "My mouth is full of ulcers and I haven't been able to drink a drop of water all day because of the pain.",
    "stated_reason_for_presenting_today": "The ulcers flared up badly and it hurts too much to swallow, so I can't get any fluids down and I'm starting to feel a bit off.",
    "encounter_type_patient_expectation": "seeking_diagnosis"
  },
  "history_as_reported": {
    "symptom_narrative": {
      "onset": "about 48 hours ago a couple of ulcers started, but they've really multiplied today",
      "duration": "48 hours, much worse in the last day",
      "character": "raw, burning, stinging sores all over the inside of my mouth",
      "severity_patient_description": "so painful I can barely swallow — it's the worst flare I've had",
      "location_as_patient_describes": "inside my cheeks and the roof/back of my mouth",
      "timing_pattern": "constant, worse whenever I try to swallow or drink",
      "what_makes_it_better": "nothing much — the paracetamol I took barely touched it",
      "what_makes_it_worse": "swallowing, drinking, anything touching the sores",
      "associated_symptoms_volunteered": "I feel a bit dizzy when I stand up and pretty tired, probably because I haven't had anything to drink",
      "previous_episodes": "I get mouth ulcers on and off, but never this many or this bad all at once",
      "functional_impact": "I can still get around the house but I'm worn out and I've basically stopped eating and drinking"
    },
    "past_medical_history": [
      {
        "condition_as_patient_states": "recurring mouth ulcers that come and go",
        "how_managed": "usually just wait them out or use over-the-counter gels"
      }
    ],
    "current_medications_as_reported": [
      {
        "name_as_patient_states": "paracetamol",
        "adherence_as_reported": "irregular",
        "otc_or_herbal": true
      }
    ],
    "allergies_as_reported": [],
    "family_history_as_reported": [],
    "social_history_volunteered": {
      "relevant_life_context": "lives on my own, so there's no one here to help me if I get worse"
    }
  },
  "objective_data_offered": [
    {
      "type": "video_observable_finding",
      "value": "lips look dry and cracked and I'm speaking with difficulty because of the mouth pain",
      "source": "video_observable",
      "verified": false,
      "reliability_caveat": "patient/self view over chat; not a clinician oral examination"
    },
    {
      "type": "symptom_report",
      "value": "I feel lightheaded when I stand up",
      "source": "patient_reported",
      "verified": false,
      "reliability_caveat": "self-reported sensation, no measured blood pressure available"
    }
  ]
}
