{
  "case_id": "SPEC-CARD-01-00257",
  "node_type": "symptom_links",
  "symptoms": [
    {
      "symptom_id": "SYM-001",
      "symptom_name": "Prodrome of visual 'greying out' and lightheadedness before collapse",
      "symptom_type": "symptom",
      "present_in_case": true,
      "elicitation_method": "history_question_sufficient",
      "disclosure_item_ref": "DI-001",
      "diagnostic_weight_edges": [
        {
          "diagnosis": "Reflex (vasovagal) syncope",
          "edge_type": "supports",
          "strength": "strong",
          "evidence_basis": "A classic autonomic prodrome is characteristic of reflex syncope."
        },
        {
          "diagnosis": "Cardiac / arrhythmic syncope",
          "edge_type": "argues_against",
          "strength": "moderate",
          "evidence_basis": "Cardiac syncope is typically sudden and unheralded ('drop attack') without a vagal prodrome."
        }
      ]
    },
    {
      "symptom_id": "SYM-002",
      "symptom_name": "Triggered by prolonged standing in a warm environment",
      "symptom_type": "risk_factor",
      "present_in_case": true,
      "elicitation_method": "directed_clinical_question_required",
      "disclosure_item_ref": "DI-002",
      "diagnostic_weight_edges": [
        {
          "diagnosis": "Reflex (vasovagal) syncope",
          "edge_type": "supports",
          "strength": "strong",
          "evidence_basis": "Prolonged orthostatic stress in heat is a recognised trigger for the vasovagal reflex."
        }
      ]
    },
    {
      "symptom_id": "SYM-003",
      "symptom_name": "Bystander-observed pallor with loss of postural tone",
      "symptom_type": "physical_sign",
      "present_in_case": true,
      "elicitation_method": "history_question_sufficient",
      "disclosure_item_ref": "DI-003",
      "diagnostic_weight_edges": [
        {
          "diagnosis": "Reflex (vasovagal) syncope",
          "edge_type": "supports",
          "strength": "moderate",
          "evidence_basis": "Profound pallor during the event reflects the vasodilatory/bradycardic reflex and points away from seizure."
        }
      ]
    },
    {
      "symptom_id": "SYM-004",
      "symptom_name": "Rapid complete recovery within ~30 seconds without postictal confusion",
      "symptom_type": "symptom",
      "present_in_case": true,
      "elicitation_method": "history_question_sufficient",
      "disclosure_item_ref": "DI-003",
      "diagnostic_weight_edges": [
        {
          "diagnosis": "Epileptic seizure",
          "edge_type": "argues_against",
          "strength": "strong",
          "evidence_basis": "Seizures are typically followed by a period of postictal confusion; rapid clear recovery favours syncope."
        }
      ]
    },
    {
      "symptom_id": "SYM-005",
      "symptom_name": "No tongue biting, no incontinence",
      "symptom_type": "pertinent_negative",
      "present_in_case": true,
      "elicitation_method": "directed_clinical_question_required",
      "disclosure_item_ref": "DI-006",
      "diagnostic_weight_edges": [
        {
          "diagnosis": "Epileptic seizure",
          "edge_type": "argues_against",
          "strength": "moderate",
          "evidence_basis": "Lateral tongue biting and incontinence favour seizure; their absence supports syncope."
        }
      ]
    },
    {
      "symptom_id": "SYM-006",
      "symptom_name": "Transient loss of consciousness with a fall",
      "symptom_type": "symptom",
      "present_in_case": true,
      "elicitation_method": "history_question_sufficient",
      "disclosure_item_ref": "DI-003",
      "diagnostic_weight_edges": [
        {
          "diagnosis": "Cardiac / arrhythmic syncope",
          "edge_type": "required_to_exclude",
          "strength": "strong",
          "evidence_basis": "Any transient loss of consciousness requires a 12-lead ECG to exclude an arrhythmic cause before it is called benign."
        }
      ]
    },
    {
      "symptom_id": "SYM-007",
      "symptom_name": "Occipital head strike with small tender haematoma, no laceration",
      "symptom_type": "physical_sign",
      "present_in_case": true,
      "elicitation_method": "requires_physical_examination",
      "disclosure_item_ref": "DI-004",
      "diagnostic_weight_edges": [
        {
          "diagnosis": "Traumatic intracranial injury from the head strike",
          "edge_type": "red_flag_for",
          "strength": "moderate",
          "evidence_basis": "A head strike with loss of consciousness is the trigger for structured head-injury observation; palpation for a step-off/fracture needs in-person assessment."
        }
      ]
    },
    {
      "symptom_id": "SYM-008",
      "symptom_name": "No chest pain, palpitations or exertion before the event",
      "symptom_type": "pertinent_negative",
      "present_in_case": true,
      "elicitation_method": "directed_clinical_question_required",
      "disclosure_item_ref": "DI-005",
      "diagnostic_weight_edges": [
        {
          "diagnosis": "Cardiac / arrhythmic syncope",
          "edge_type": "argues_against",
          "strength": "moderate",
          "evidence_basis": "Exertional onset and palpitations raise the probability of cardiac syncope; their absence is reassuring but not exclusionary."
        }
      ]
    },
    {
      "symptom_id": "SYM-009",
      "symptom_name": "Negative orthostatic vitals (no significant postural blood-pressure drop)",
      "symptom_type": "physical_sign",
      "present_in_case": true,
      "elicitation_method": "cannot_be_elicited_via_telehealth",
      "diagnostic_weight_edges": [
        {
          "diagnosis": "Orthostatic hypotension",
          "edge_type": "argues_against",
          "strength": "moderate",
          "evidence_basis": "Measured lying/standing blood pressures were negative — a clinician measurement not obtainable over chat, hence sealed."
        }
      ]
    },
    {
      "symptom_id": "SYM-010",
      "symptom_name": "Normal neurological examination (cranial nerves, power, coordination, pupils intact)",
      "symptom_type": "physical_sign",
      "present_in_case": true,
      "elicitation_method": "requires_physical_examination",
      "diagnostic_weight_edges": [
        {
          "diagnosis": "Traumatic intracranial injury from the head strike",
          "edge_type": "argues_against",
          "strength": "moderate",
          "evidence_basis": "A normal in-person neurological exam is reassuring but is exactly the assessment telehealth cannot perform, so it remains a sealed clinician finding."
        }
      ]
    },
    {
      "symptom_id": "SYM-011",
      "symptom_name": "Poor oral intake with dry mucosa (mild dehydration)",
      "symptom_type": "risk_factor",
      "present_in_case": true,
      "elicitation_method": "history_question_sufficient",
      "disclosure_item_ref": "DI-007",
      "diagnostic_weight_edges": [
        {
          "diagnosis": "Reflex (vasovagal) syncope",
          "edge_type": "supports",
          "strength": "weak",
          "evidence_basis": "Volume depletion lowers the threshold for the vasovagal reflex on prolonged standing."
        }
      ]
    }
  ],
  "symptom_clusters": [
    {
      "cluster_id": "SC-001",
      "cluster_name": "Classic reflex-syncope tetrad",
      "constituent_symptom_ids": [
        "SYM-001",
        "SYM-003",
        "SYM-004",
        "SYM-005"
      ],
      "target_diagnosis": "Reflex (vasovagal) syncope",
      "clinical_significance": "Prodrome + pallor + rapid recovery + absence of seizure features together make a reflex faint the leading explanation and argue strongly against seizure.",
      "cumulative_strength": "very_strong",
      "all_items_required": false
    }
  ],
  "investigation_recommendations_expected": [
    {
      "investigation_name": "12-lead ECG",
      "priority": "urgent",
      "rationale": "Minimum first-line test to exclude an arrhythmic or structural cardiac cause of a first syncope; cannot be performed via telehealth, so it drives the same-day in-person disposition."
    },
    {
      "investigation_name": "In-person neurological examination and head-injury observation",
      "priority": "urgent",
      "rationale": "Required to assess the head strike with loss of consciousness for an evolving intracranial injury."
    },
    {
      "investigation_name": "Lying and standing blood pressure",
      "priority": "semi_urgent",
      "rationale": "Assesses for an orthostatic contribution; requires measured vitals not obtainable over chat."
    }
  ]
}
