{
  "case_id": "SPEC-ENDO-04-00204",
  "demographics": {
    "age": 35,
    "sex_at_birth": "female",
    "living_situation": "lives alone",
    "geographic_context": "RA1_major_city",
    "language_and_literacy": {
      "primary_language": "English",
      "english_proficiency": "fluent",
      "health_literacy_level": "moderate"
    },
    "contact_nok": {
      "relationship": "not stated",
      "available": false
    }
  },
  "opening_complaint": {
    "verbatim_patient_text": "My hands keep locking up into claws, my lips are completely numb, and I have absolutely no energy left to stand.",
    "stated_reason_for_presenting_today": "It's been building for a couple of days and today the cramping and numbness got much worse — I'm frightened and I live on my own.",
    "encounter_type_patient_expectation": "seeking_diagnosis"
  },
  "history_as_reported": {
    "symptom_narrative": {
      "onset": "started about 48 hours ago with tingling around my mouth and in my fingers",
      "duration": "about two days, and much worse today",
      "character": "tingling and numbness around my lips and fingers that today turned into painful cramps, with my hands seizing up into claw shapes",
      "severity_patient_description": "really bad now — the cramps are painful and I can barely stand up",
      "location_as_patient_describes": "around my mouth, my fingers and hands, and my legs feel weak",
      "timing_pattern": "it's been coming on steadily and getting worse, with spasms coming in waves",
      "what_makes_it_better": "nothing seems to help",
      "what_makes_it_worse": "it just keeps getting worse, and I feel dizzy when I stand up",
      "associated_symptoms_volunteered": "I've had no energy at all, I feel weak and wiped out, and I get lightheaded standing up",
      "previous_episodes": "I've had tingling before but never this bad and never with my hands cramping like this",
      "functional_impact": "I can hardly move around because of the cramps and how exhausted I am"
    },
    "past_medical_history": [
      {
        "condition_as_patient_states": "thrush in my mouth that keeps coming back — I've had it on and off since I was a kid",
        "how_managed": "antifungal treatments on and off"
      },
      {
        "condition_as_patient_states": "white patches on my skin where I've lost colour",
        "how_managed": "nothing much, just told it was harmless"
      },
      {
        "condition_as_patient_states": "some patches of hair loss on my scalp"
      },
      {
        "condition_as_patient_states": "I've lost some weight recently without trying, and lately I feel the cold more than I used to"
      }
    ],
    "current_medications_as_reported": [
      {
        "name_as_patient_states": "over-the-counter calcium tablets",
        "adherence_as_reported": "irregular",
        "otc_or_herbal": true
      }
    ],
    "allergies_as_reported": [],
    "family_history_as_reported": [],
    "social_history_volunteered": {
      "relevant_life_context": "I live by myself, so there's no one here with me right now if things get worse"
    }
  },
  "objective_data_offered": [
    {
      "type": "video_observable_finding",
      "value": "on video my hands keep drawing up and cramping into claw-like shapes on and off",
      "source": "video_observable",
      "verified": false,
      "reliability_caveat": "patient-observed on chat video; not a clinician examination"
    },
    {
      "type": "symptom_observation",
      "value": "my lips and fingers feel numb and tingly",
      "source": "patient_reported",
      "verified": false
    },
    {
      "type": "symptom_observation",
      "value": "I feel lightheaded and unsteady when I stand up",
      "source": "patient_reported",
      "verified": false
    }
  ]
}
