{
  "case_id": "SPEC-MSK-01-00225",
  "node_type": "symptom_links",
  "symptoms": [
    {
      "symptom_id": "SYM-001",
      "symptom_name": "Low-impact mechanical fall from standing height",
      "symptom_type": "risk_factor",
      "present_in_case": true,
      "disclosure_item_ref": "DI-001",
      "elicitation_method": "history_question_sufficient",
      "diagnostic_weight_edges": [
        {
          "diagnosis": "Fractured neck of femur",
          "edge_type": "supports",
          "strength": "strong",
          "evidence_basis": "In an osteoporotic elder a standing-height fall is the classic fragility-fracture mechanism."
        },
        {
          "diagnosis": "Pelvic ramus fracture",
          "edge_type": "supports",
          "strength": "moderate",
          "evidence_basis": "Same mechanism can fracture the pelvic ring."
        }
      ]
    },
    {
      "symptom_id": "SYM-002",
      "symptom_name": "Severe deep groin and hip pain, worst on movement",
      "symptom_type": "symptom",
      "present_in_case": true,
      "disclosure_item_ref": "DI-003",
      "elicitation_method": "history_question_sufficient",
      "diagnostic_weight_edges": [
        {
          "diagnosis": "Fractured neck of femur",
          "edge_type": "supports",
          "strength": "strong",
          "evidence_basis": "Groin/hip pain localised and movement-provoked is typical of proximal femoral fracture."
        }
      ]
    },
    {
      "symptom_id": "SYM-003",
      "symptom_name": "Complete inability to bear weight on the affected limb",
      "symptom_type": "functional_finding",
      "present_in_case": true,
      "disclosure_item_ref": "DI-002",
      "elicitation_method": "history_question_sufficient",
      "diagnostic_weight_edges": [
        {
          "diagnosis": "Fractured neck of femur",
          "edge_type": "red_flag_for",
          "strength": "strong",
          "evidence_basis": "Inability to weight-bear after a fall is a cardinal red flag for significant fracture — mandates imaging."
        },
        {
          "diagnosis": "Severe soft-tissue contusion",
          "edge_type": "argues_against",
          "strength": "moderate",
          "evidence_basis": "A simple contusion rarely abolishes weight-bearing entirely."
        }
      ]
    },
    {
      "symptom_id": "SYM-004",
      "symptom_name": "Shortened and externally rotated limb",
      "symptom_type": "physical_sign",
      "present_in_case": true,
      "elicitation_method": "requires_physical_examination",
      "diagnostic_weight_edges": [
        {
          "diagnosis": "Fractured neck of femur",
          "edge_type": "pathognomonic_for",
          "strength": "definitive",
          "evidence_basis": "The classic shortened/externally rotated limb is the hallmark deformity of a displaced NOF fracture. SEALED — requires clinician inspection; withheld from the AI-Doctor-readable layer."
        },
        {
          "diagnosis": "Hip dislocation",
          "edge_type": "argues_against",
          "strength": "moderate",
          "evidence_basis": "Posterior dislocation classically shows internal rotation, not external."
        }
      ]
    },
    {
      "symptom_id": "SYM-005",
      "symptom_name": "Greater-trochanter bony tenderness and pain on passive internal rotation",
      "symptom_type": "physical_sign",
      "present_in_case": true,
      "elicitation_method": "requires_physical_examination",
      "diagnostic_weight_edges": [
        {
          "diagnosis": "Fractured neck of femur",
          "edge_type": "supports",
          "strength": "strong",
          "evidence_basis": "Focal bony tenderness and exquisite pain on rotation support a proximal femoral fracture — clinician-elicited, sealed."
        }
      ]
    },
    {
      "symptom_id": "SYM-006",
      "symptom_name": "Intact distal pulses and foot sensation (no gross neurovascular compromise)",
      "symptom_type": "physical_sign",
      "present_in_case": true,
      "elicitation_method": "requires_physical_examination",
      "diagnostic_weight_edges": [
        {
          "diagnosis": "Fractured neck of femur",
          "edge_type": "non_specific_neutral",
          "strength": "weak",
          "evidence_basis": "Reassuring pertinent finding that does not change the need for emergency transport — clinician-examined, sealed."
        }
      ]
    },
    {
      "symptom_id": "SYM-007",
      "symptom_name": "Cortical disruption on plain hip radiograph",
      "symptom_type": "investigation_result",
      "present_in_case": false,
      "elicitation_method": "requires_specific_investigation",
      "investigation_details": {
        "investigation_name": "Plain radiograph of hip / pelvis (AP and lateral)",
        "expected_result": "Cortical disruption of the femoral neck confirming fracture (MRI if occult and clinical suspicion remains)",
        "is_appropriate_first_line": true,
        "if_not_ordered_consequence": "Fracture remains unconfirmed and surgical planning is delayed; a non-weight-bearing faller cannot be cleared clinically."
      },
      "diagnostic_weight_edges": [
        {
          "diagnosis": "Fractured neck of femur",
          "edge_type": "pathognomonic_for",
          "strength": "definitive",
          "evidence_basis": "Radiographic cortical disruption is the confirmatory test — hospital investigation, never available via telehealth."
        }
      ]
    },
    {
      "symptom_id": "SYM-008",
      "symptom_name": "Known severe osteoporosis with previous fragility (Colles) fracture",
      "symptom_type": "risk_factor",
      "present_in_case": true,
      "disclosure_item_ref": "DI-004",
      "elicitation_method": "history_question_sufficient",
      "diagnostic_weight_edges": [
        {
          "diagnosis": "Fractured neck of femur",
          "edge_type": "supports",
          "strength": "strong",
          "evidence_basis": "Established osteoporosis and a prior fragility fracture markedly raise the pre-test probability of a new fragility fracture."
        }
      ]
    },
    {
      "symptom_id": "SYM-009",
      "symptom_name": "Pallor, diaphoresis and tachycardia (measured HR ~110)",
      "symptom_type": "physical_sign",
      "present_in_case": true,
      "disclosure_item_ref": "DI-005",
      "elicitation_method": "cannot_be_elicited_via_telehealth",
      "diagnostic_weight_edges": [
        {
          "diagnosis": "Fractured neck of femur",
          "edge_type": "supports",
          "strength": "moderate",
          "evidence_basis": "May reflect pain and early hypovolaemia from occult thigh haemorrhage. The pale/sweaty appearance is carer-observable (DI-005); the measured heart rate is a clinician/device value and is sealed."
        }
      ]
    }
  ],
  "investigation_recommendations_expected": [
    {
      "investigation_name": "Plain radiograph of hip and pelvis",
      "priority": "immediate",
      "unlocks_symptom_id": "SYM-007",
      "rationale": "Confirms the fracture and guides surgical planning; performed on ED arrival, not obtainable via telehealth."
    },
    {
      "investigation_name": "Bloods (FBE, U&E/creatinine, group and hold, coagulation)",
      "priority": "immediate",
      "rationale": "Assess for anaemia from occult blood loss, renal function and long-lie complications (rhabdomyolysis/AKI); pre-operative workup — hospital-based."
    },
    {
      "investigation_name": "Remote attempt to obtain a home BP or examine the leg by the AI Doctor",
      "priority": "not_recommended",
      "rationale": "The AI cannot measure vitals without a device or inspect/palpate the limb; time must not be spent on this instead of calling 000."
    }
  ]
}
