{
  "symptoms": [
    {
      "symptom_id": "SYM-001",
      "symptom_name": "Intensely pruritic grouped vesicles",
      "symptom_type": "symptom",
      "present_in_case": true,
      "fhir_path": "Condition._freetext_HPC_tags.character",
      "snomed_ref": {
        "system": "SNOMED_CT",
        "code": "418290006",
        "display": "Itching"
      },
      "elicitation_method": "history_question_sufficient",
      "onset": "24 hours ago",
      "diagnostic_weight_edges": [
        {
          "diagnosis": "Dermatitis herpetiformis",
          "edge_type": "supports",
          "strength": "moderate",
          "evidence_basis": "Intensely itchy grouped vesicles are characteristic."
        }
      ]
    },
    {
      "symptom_id": "SYM-002",
      "symptom_name": "Symmetric extensor distribution; no burrows; no affected contacts",
      "symptom_type": "physical_sign",
      "present_in_case": true,
      "fhir_path": "Condition._freetext_HPC_tags.character",
      "disclosure_item_ref": "DI-001",
      "elicitation_method": "directed_clinical_question_required",
      "diagnostic_weight_edges": [
        {
          "diagnosis": "Dermatitis herpetiformis",
          "edge_type": "pathognomonic_for",
          "strength": "strong",
          "evidence_basis": "Symmetric extensor grouped vesicles are highly characteristic of dermatitis herpetiformis."
        },
        {
          "diagnosis": "Scabies",
          "edge_type": "argues_against",
          "strength": "strong",
          "evidence_basis": "No web-space burrows and no itchy contacts strongly argue against scabies."
        }
      ]
    },
    {
      "symptom_id": "SYM-003",
      "symptom_name": "Non-dermatomal bilateral distribution",
      "symptom_type": "pertinent_negative",
      "present_in_case": true,
      "fhir_path": "Condition._freetext_HPC_tags.site_radiation",
      "disclosure_item_ref": "DI-002",
      "elicitation_method": "directed_clinical_question_required",
      "diagnostic_weight_edges": [
        {
          "diagnosis": "Herpes zoster",
          "edge_type": "argues_against",
          "strength": "strong",
          "evidence_basis": "Bilateral symmetric distribution excludes dermatomal zoster."
        }
      ]
    },
    {
      "symptom_id": "SYM-004",
      "symptom_name": "No secondary infection (no spreading warmth/pus/fever)",
      "symptom_type": "pertinent_negative",
      "present_in_case": true,
      "fhir_path": "Condition._freetext_HPC_tags.associated_symptoms",
      "disclosure_item_ref": "DI-003",
      "elicitation_method": "history_question_sufficient",
      "diagnostic_weight_edges": [
        {
          "diagnosis": "Dermatitis herpetiformis",
          "edge_type": "non_specific_neutral",
          "strength": "weak",
          "evidence_basis": "Absence of secondary infection allows outpatient management."
        }
      ]
    }
  ],
  "investigation_recommendations_expected": [
    {
      "investigation_name": "Skin biopsy with direct immunofluorescence",
      "priority": "semi_urgent",
      "rationale": "Confirms dermatitis herpetiformis; via in-person GP/dermatology."
    },
    {
      "investigation_name": "Coeliac serology (tTG-IgA, total IgA)",
      "priority": "routine",
      "rationale": "Identifies associated gluten sensitivity to guide dietary treatment."
    },
    {
      "investigation_name": "Empirical scabies treatment for the whole household",
      "priority": "not_recommended",
      "rationale": "Not indicated given the symmetric extensor pattern, no burrows and no affected contacts."
    }
  ],
  "case_id": "SPEC-DERM-03-00012",
  "node_type": "symptom_links"
}
