{
  "case_id": "SPEC-MSK-01-00012",
  "demographics": {
    "age": 34,
    "sex_at_birth": "male",
    "living_situation": "lives alone",
    "language_and_literacy": {
      "primary_language": "English",
      "english_proficiency": "fluent",
      "health_literacy_level": "moderate"
    },
    "contact_nok": {
      "relationship": "none stated",
      "available": false
    }
  },
  "opening_complaint": {
    "verbatim_patient_text": "My calf muscle suddenly locked up into a rock-hard knot, and the pain is so intense I thought the muscle tore in half.",
    "stated_reason_for_presenting_today": "It seized up right after a long run and won't fully let go — I can't put weight on it.",
    "encounter_type_patient_expectation": "seeking_diagnosis"
  },
  "history_as_reported": {
    "symptom_narrative": {
      "onset": "90 minutes ago, right after a 15km run in warm weather",
      "duration": "~90 min, recurring on rest",
      "character": "intense involuntary cramp, hard knot in the calf",
      "severity_patient_description": "agonising, can't bear weight",
      "location_as_patient_describes": "my right calf",
      "timing_pattern": "eases with stretch then recurs at rest",
      "what_makes_it_better": "stretching briefly",
      "what_makes_it_worse": "resting, pointing the toes",
      "associated_symptoms_volunteered": "sweated a lot on the run; no chest pain, no breathlessness",
      "previous_episodes": "cramps with hard exercise before",
      "functional_impact": "can't walk on it"
    },
    "past_medical_history": [],
    "current_medications_as_reported": [
      {
        "name_as_patient_states": "ibuprofen",
        "dose_as_patient_reports": "400mg 30 min ago, no effect",
        "adherence_as_reported": "irregular",
        "otc_or_herbal": true
      }
    ],
    "allergies_as_reported": [
      {
        "substance": "no known drug allergy",
        "reaction_described": "none known"
      }
    ],
    "family_history_as_reported": [],
    "social_history_volunteered": {
      "relevant_life_context": "lives alone; intense endurance exercise with heavy sweating and limited fluids"
    }
  },
  "objective_data_offered": [
    {
      "type": "muscle",
      "value": "visible/palpable hard knot in the right calf; eases a little with stretch",
      "source": "patient_reported",
      "verified": false
    },
    {
      "type": "limb",
      "value": "foot warm, can feel and wiggle toes normally",
      "source": "patient_reported",
      "verified": false,
      "reliability_caveat": "self-assessed perfusion/neuro"
    }
  ],
  "digital_tablet_field_map": {
    "chief_complaint_path": "Condition._freetext_HPC_tags",
    "demographics_path": "Patient"
  }
}
