{
  "symptoms": [
    {
      "symptom_id": "SYM-001",
      "symptom_name": "Frequent small-volume rectal bleeding with mucus and tenesmus",
      "symptom_type": "symptom",
      "present_in_case": true,
      "fhir_path": "Condition._freetext_HPC_tags.character",
      "snomed_ref": {
        "system": "SNOMED_CT",
        "code": "2764000",
        "display": "Rectal haemorrhage"
      },
      "elicitation_method": "history_question_sufficient",
      "onset": "this evening",
      "diagnostic_weight_edges": [
        {
          "diagnosis": "Ulcerative proctitis flare",
          "edge_type": "supports",
          "strength": "strong",
          "evidence_basis": "Small-volume blood-and-mucus stools with tenesmus are characteristic of proctitis."
        }
      ]
    },
    {
      "symptom_id": "SYM-002",
      "symptom_name": "Small-volume bleeding; no postural syncope",
      "symptom_type": "pertinent_negative",
      "present_in_case": true,
      "fhir_path": "Condition._freetext_HPC_tags.character",
      "disclosure_item_ref": "DI-001",
      "elicitation_method": "directed_clinical_question_required",
      "diagnostic_weight_edges": [
        {
          "diagnosis": "Major lower GI bleed",
          "edge_type": "argues_against",
          "strength": "strong",
          "evidence_basis": "Small volumes with stable posture argue strongly against a haemodynamically significant bleed."
        }
      ]
    },
    {
      "symptom_id": "SYM-003",
      "symptom_name": "Afebrile, soft abdomen, no perianal mass",
      "symptom_type": "pertinent_negative",
      "present_in_case": true,
      "fhir_path": "Condition._freetext_HPC_tags.associated_symptoms",
      "disclosure_item_ref": "DI-002",
      "elicitation_method": "directed_clinical_question_required",
      "diagnostic_weight_edges": [
        {
          "diagnosis": "Perirectal abscess / toxic colitis",
          "edge_type": "argues_against",
          "strength": "moderate",
          "evidence_basis": "No fever, perianal mass or rigidity lowers abscess/toxic-colitis probability."
        }
      ]
    },
    {
      "symptom_id": "SYM-004",
      "symptom_name": "Lapsed topical mesalazine in known proctitis",
      "symptom_type": "risk_factor",
      "present_in_case": true,
      "fhir_path": "Condition._freetext_HPC_tags.precipitating_factors",
      "disclosure_item_ref": "DI-003",
      "elicitation_method": "history_question_sufficient",
      "diagnostic_weight_edges": [
        {
          "diagnosis": "Ulcerative proctitis flare",
          "edge_type": "supports",
          "strength": "moderate",
          "evidence_basis": "Lapsed topical therapy is a common flare trigger."
        }
      ]
    }
  ],
  "investigation_recommendations_expected": [
    {
      "investigation_name": "Routine/urgent GP-gastroenterology review with FBC/CRP and stool tests",
      "priority": "semi_urgent",
      "rationale": "Assess flare severity and exclude infection; arrange maintenance therapy."
    },
    {
      "investigation_name": "Emergency endoscopy/transfusion",
      "priority": "not_recommended",
      "unlocks_symptom_id": "SYM-002",
      "rationale": "Only if a major bleed (large-volume/postural syncope) develops."
    }
  ],
  "case_id": "SPEC-GI-03-00047",
  "node_type": "symptom_links"
}
