{
  "case_id": "SPEC-RESP-01-00006",
  "node_type": "symptom_links",
  "symptoms": [
    {
      "symptom_id": "SYM-001",
      "symptom_name": "Facial pain/pressure worse on bending forward",
      "symptom_type": "symptom",
      "present_in_case": true,
      "fhir_path": "Condition._freetext_HPC_tags.character",
      "snomed_ref": {
        "system": "SNOMED_CT",
        "code": "25064002",
        "display": "Headache"
      },
      "elicitation_method": "history_question_sufficient",
      "diagnostic_weight_edges": [
        {
          "diagnosis": "Acute viral rhinosinusitis",
          "edge_type": "supports",
          "strength": "strong",
          "evidence_basis": "Positional facial pressure over sinuses is characteristic of sinusitis."
        }
      ]
    },
    {
      "symptom_id": "SYM-002",
      "symptom_name": "Purulent nasal discharge and hyposmia",
      "symptom_type": "symptom",
      "present_in_case": true,
      "fhir_path": "Condition._freetext_HPC_tags.associated_symptoms",
      "elicitation_method": "history_question_sufficient",
      "diagnostic_weight_edges": [
        {
          "diagnosis": "Acute viral rhinosinusitis",
          "edge_type": "supports",
          "strength": "moderate",
          "evidence_basis": "Purulent discharge occurs in viral sinusitis and does NOT by itself indicate bacterial infection."
        },
        {
          "diagnosis": "Acute bacterial rhinosinusitis",
          "edge_type": "non_specific_neutral",
          "strength": "weak",
          "evidence_basis": "Purulence alone is non-discriminating before 10 days."
        }
      ]
    },
    {
      "symptom_id": "SYM-003",
      "symptom_name": "Duration <10 days without double-sickening",
      "symptom_type": "pertinent_negative",
      "present_in_case": true,
      "fhir_path": "Condition._freetext_HPC_tags.duration",
      "disclosure_item_ref": "DI-003",
      "elicitation_method": "history_question_sufficient",
      "diagnostic_weight_edges": [
        {
          "diagnosis": "Acute bacterial rhinosinusitis",
          "edge_type": "argues_against",
          "strength": "moderate",
          "evidence_basis": "Short duration and monophasic course argue against bacterial sinusitis."
        }
      ]
    },
    {
      "symptom_id": "SYM-004",
      "symptom_name": "No periorbital swelling / normal eye movements (examination)",
      "symptom_type": "pertinent_negative",
      "present_in_case": true,
      "fhir_path": "Condition._freetext_HPC_tags.associated_symptoms",
      "disclosure_item_ref": "DI-001",
      "elicitation_method": "directed_clinical_question_required",
      "diagnostic_weight_edges": [
        {
          "diagnosis": "Orbital cellulitis",
          "edge_type": "argues_against",
          "strength": "strong",
          "evidence_basis": "Normal eyes/eye movements argue strongly against orbital cellulitis."
        }
      ]
    },
    {
      "symptom_id": "SYM-005",
      "symptom_name": "Sinus tenderness on palpation; purulent middle-meatus discharge (examination)",
      "symptom_type": "physical_sign",
      "present_in_case": true,
      "fhir_path": "Condition._freetext_examination_tags.sinuses",
      "elicitation_method": "requires_physical_examination",
      "diagnostic_weight_edges": [
        {
          "diagnosis": "Acute viral rhinosinusitis",
          "edge_type": "supports",
          "strength": "moderate",
          "evidence_basis": "Tenderness with middle-meatus pus supports sinusitis but requires examination."
        }
      ]
    }
  ],
  "investigation_recommendations_expected": [
    {
      "investigation_name": "No acute imaging/bloods",
      "priority": "not_recommended",
      "rationale": "Uncomplicated acute sinusitis is clinical; imaging only for suspected complications."
    },
    {
      "investigation_name": "CT sinuses/orbits",
      "priority": "not_recommended",
      "rationale": "Reserved for suspected orbital/intracranial complication — not this presentation."
    }
  ]
}
